powerpoint2pdf/__main__.py
powerpoint2pdf/main.py
ppt2pdf/__main__.py
ppt2pdf/main.py
powerpoint2pdf-1.0.1.dist-info/LICENSE
powerpoint2pdf-1.0.1.dist-info/METADATA
powerpoint2pdf-1.0.1.dist-info/WHEEL
powerpoint2pdf-1.0.1.dist-info/entry_points.txt
powerpoint2pdf-1.0.1.dist-info/top_level.txt
powerpoint2pdf-1.0.1.dist-info/RECORD
