Metadata-Version: 2.1
Name: powerpoint2pdf
Version: 1.0.1
Summary: =?unknown-8bit?b?5bCGUFBU55qE6aG16Z2i5a+85Ye65Li6UERG?=
Home-page: https://github.com/OpenHUTB/ppt2pdf
Author: OpenHUTB
Author-email: 2929@hutb.edu.cn
Classifier: Programming Language :: Python :: 3
Classifier: License :: OSI Approved :: MIT License
Classifier: Operating System :: OS Independent
Requires-Python: >=3.6
License-File: LICENSE
Requires-Dist: comtypes
Requires-Dist: pdfCropMargins
